{"pageProps":{"menclothe":{"_createdAt":"2023-03-14T11:42:37Z","_id":"e5b513ef-ce26-4144-bb79-5c5ea221c913","_rev":"71xTIiICbzxv6Ny0SxvNVK","_type":"mensclothe","_updatedAt":"2023-03-23T06:59:49Z","brand":"Allen Solly","category":"pants","code":"allen-solly-mens-sweat-pants","color":"navy","fulldesc":["Care Instructions: Machine Wash","Fit Type: Slim","allen-solly-navy-trousers","machine wash as per tag","Material : 69% Cotton and 31% Linen"],"image":[{"_key":"0e61301e5a46","_type":"image","asset":{"_ref":"image-fd020ec670c6664fab6b0d3a7f0adcbec1f75a74-1000x1500-jpg","_type":"reference"}},{"_key":"92b929048271","_type":"image","asset":{"_ref":"image-9df2ee4e958322a6088b35cd804b765f991cea29-1000x1500-jpg","_type":"reference"}},{"_key":"f29ba5cc23d0","_type":"image","asset":{"_ref":"image-5c162766d62c2c87e51445d9211d2c2d38a8a847-1000x1500-jpg","_type":"reference"}},{"_key":"4af68206ae63","_type":"image","asset":{"_ref":"image-e6b2256fd3199af109a193ff531d464345b6742b-1000x1500-jpg","_type":"reference"}}],"material":"cotton","mrp":2999,"name":"Allen Solly Men's Slim Casual Trousers 34 navy","print":"solid","saleprice":1440,"shortdesc":"Allen Solly Men's Slim Casual Trousers 34 navy","size":"34","slug":{"_type":"slug","current":"allen-solly-men-s-slim-casual-trousers-34-navy"},"subcategory":"casual","subcategory1":"machine wash","tags":["mens clothes","allen solly","trousers","slim fit","casual","34","navy"]}},"__N_SSG":true}